LICENSE.txt
README.md
setup.py
sotiimpackage/__init__.py
sotiimpackage/__main__.py
sotiimpackage/workshops.py
sotiimpackage.egg-info/PKG-INFO
sotiimpackage.egg-info/SOURCES.txt
sotiimpackage.egg-info/dependency_links.txt
sotiimpackage.egg-info/requires.txt
sotiimpackage.egg-info/top_level.txt