Metadata-Version: 2.1
Name: sotiimpackage
Version: 0.0.1
Summary: Consume Api de Codigo facilito
Home-page: https://github.com/Sotiim/Curso-Py-Package
Author: Cesar Alberto Garcia Aranda
Author-email: csrrnld@gmail.com
License: MIT
Keywords: codigofacilito,Sotiim
Platform: UNKNOWN
Classifier: Development Status :: 3 - Alpha
Classifier: Intended Audience :: Developers
Classifier: Topic :: Software Development :: Build Tools
Classifier: License :: OSI Approved :: MIT License
Classifier: Programming Language :: Python :: 3
License-File: LICENSE.txt
